<annotation verified="no"><folder>mydata_yibiao</folder><filename>l(12)</filename><path>C:\Users\xxa\Desktop\mydata_yibiao\l(12).jpg</path><source><database>Unknown</database></source><size><width>343</width><height>340</height><depth>3</depth></size><segmented>0</segmented><object><type>robndbox</type><name>11</name><pose>Unspecified</pose><truncated>0</truncated><difficult>0</difficult><robndbox><cx>190.9907</cx><cy>159.0756</cy><w>160.7897</w><h>97.3635</h><angle>0.32</angle></robndbox></object></annotation>