<annotation verified="no"><folder>mydata_yibiao</folder><filename>l(209)</filename><path>C:\Users\xxa\Desktop\mydata_yibiao\l(209).jpg</path><source><database>Unknown</database></source><size><width>501</width><height>577</height><depth>3</depth></size><segmented>0</segmented><object><type>robndbox</type><name>5</name><pose>Unspecified</pose><truncated>0</truncated><difficult>0</difficult><robndbox><cx>276.0079</cx><cy>254.7107</cy><w>268.1946</w><h>247.7782</h><angle>0.06</angle></robndbox></object></annotation>