<annotation verified="no"><folder>mydata_yibiao</folder><filename>l(471)</filename><path>C:\Users\xxa\Desktop\mydata_yibiao\l(471).jpg</path><source><database>Unknown</database></source><size><width>668</width><height>732</height><depth>3</depth></size><segmented>0</segmented><object><type>robndbox</type><name>25</name><pose>Unspecified</pose><truncated>0</truncated><difficult>0</difficult><bndbox><x0>180.42860000000002</x0><y0>117.8571</y0><x1>534.4286</x1><y1>117.8571</y1><x2>534.4286</x2><y2>479.8571</y2><x3>180.42860000000002</x3><y3>479.8571</y3></bndbox></object></annotation>