<annotation verified="no"><folder>mydata_yibiao</folder><filename>l(505)</filename><path>C:\Users\xxa\Desktop\mydata_yibiao\l(505).jpg</path><source><database>Unknown</database></source><size><width>688</width><height>741</height><depth>3</depth></size><segmented>0</segmented><object><type>robndbox</type><name>27</name><pose>Unspecified</pose><truncated>0</truncated><difficult>0</difficult><bndbox><x0>568.1871791501904</x0><y0>479.8855830584122</y0><x1>208.38718372159286</x1><y1>505.11267540912036</y1><x2>182.84202084980956</x2><y2>140.77621694158782</y2><x3>542.6420162784071</x3><y3>115.54912459087959</y3></bndbox></object></annotation>