<annotation verified="no"><folder>mydata_yibiao</folder><filename>l(92)</filename><path>C:\Users\xxa\Desktop\mydata_yibiao\l(92).jpg</path><source><database>Unknown</database></source><size><width>263</width><height>307</height><depth>3</depth></size><segmented>0</segmented><object><type>robndbox</type><name>18</name><pose>Unspecified</pose><truncated>0</truncated><difficult>0</difficult><bndbox><x0>79.25120000000001</x0><y0>51.7919</y0><x1>216.2512</x1><y1>51.7919</y1><x2>216.2512</x2><y2>209.7919</y2><x3>79.25120000000001</x3><y3>209.7919</y3></bndbox></object></annotation>