<annotation verified="no"><folder>yibiao319</folder><filename>p(67)</filename><path>C:\Users\xxa\Desktop\yibiao319\p(67).jpg</path><source><database>Unknown</database></source><size><width>2492</width><height>2330</height><depth>3</depth></size><segmented>0</segmented><object><type>robndbox</type><name>Scale</name><pose>Unspecified</pose><truncated>0</truncated><difficult>0</difficult><bndbox><x0>681.3737431253433</x0><y0>1792.3429190014494</y0><x1>732.27268853578</x1><y1>1838.8182133104192</y1><x2>536.3336568746568</x2><y2>2053.4072809985505</y2><x3>485.43471146421996</x3><y3>2006.9319866895808</y3></bndbox></object><object><type>robndbox</type><name>Scale</name><pose>Unspecified</pose><truncated>0</truncated><difficult>0</difficult><bndbox><x0>2041.533781307797</x0><y0>1941.8800607436915</y0><x1>1979.1947720165751</x1><y1>2008.689586058866</y1><x2>1754.272818692203</x2><y2>1798.8181392563083</y2><x3>1816.6118279834247</x3><y3>1732.0086139411337</y3></bndbox></object><object><type>robndbox</type><name>Pointer</name><pose>Unspecified</pose><truncated>0</truncated><difficult>0</difficult><bndbox><x0>1726.5609195800866</x0><y0>413.08865171513014</y0><x1>1759.27275608461</x1><y1>431.8182006950534</y1><x2>1590.6008804199132</x2><y2>726.4097482848698</y2><x3>1557.88904391539</x3><y3>707.6801993049465</y3></bndbox></object><object><type>robndbox</type><name>Scale2</name><pose>Unspecified</pose><truncated>0</truncated><difficult>0</difficult><bndbox><x0>1267.2727292647642</x0><y0>576.8182183418903</y0><x1>1150.4967494195378</x1><y1>582.6618473168825</y1><x2>1140.0974707352357</x2><y2>374.84818165810964</y2><x3>1256.873450580462</x3><y3>369.0045526831174</y3></bndbox></object></annotation>