<annotation verified="no"><folder>mydata_yibiao</folder><filename>l(568)</filename><path>C:\Users\xxa\Desktop\mydata_yibiao\l(568).jpg</path><source><database>Unknown</database></source><size><width>158</width><height>197</height><depth>3</depth></size><segmented>0</segmented><object><type>robndbox</type><name>49</name><pose>Unspecified</pose><truncated>0</truncated><difficult>0</difficult><bndbox><x0>33.2</x0><y0>39.0</y0><x1>116.2</x1><y1>39.0</y1><x2>116.2</x2><y2>139.0</y2><x3>33.2</x3><y3>139.0</y3></bndbox></object></annotation>